enbid_ananke/__init__.py
enbid_ananke/__metadata__.py
enbid_ananke/_builtin_utils.py
enbid_ananke/_constants.py
enbid_ananke/_defaults.py
enbid_ananke/_name.py
enbid_ananke/_templates.py
enbid_ananke/_version.py
enbid_ananke/utils.py
enbid_ananke/Enbid-2.0/.DS_Store
enbid_ananke/Enbid-2.0/COPYING
enbid_ananke/Enbid-2.0/COPYRIGHT
enbid_ananke/Enbid-2.0/Enbid
enbid_ananke/Enbid-2.0/periodic_lengths.txt
enbid_ananke/Enbid-2.0/Documentation/enbid.pdf
enbid_ananke/Enbid-2.0/Documentation/users-guide.pdf
enbid_ananke/Enbid-2.0/Documentation/users-guide.tex
enbid_ananke/Enbid-2.0/Documentation/users-guide.tex.flc
enbid_ananke/Enbid-2.0/Examples/hernquist1_small/snapshot_ici
enbid_ananke/Enbid-2.0/Examples/hernquist1_small/snapshot_ici_typelist
enbid_ananke/Enbid-2.0/Examples/uniform_6d_box_4/snapshot_ici
enbid_ananke/Enbid-2.0/Examples/uniform_6d_box_4/snapshot_ici_3d.ascii
enbid_ananke/Enbid-2.0/Examples/uniform_6d_box_4/snapshot_ici_6d.ascii
enbid_ananke/Enbid-2.0/parameterfiles/myparameterfile1
enbid_ananke/Enbid-2.0/parameterfiles/myparameterfile2
enbid_ananke/Enbid-2.0/parameterfiles/myparameterfile3
enbid_ananke/Enbid-2.0/parameterfiles/myparameterfile4
enbid_ananke/Enbid-2.0/src/Makefile
enbid_ananke/Enbid-2.0/src/allocate.cpp
enbid_ananke/Enbid-2.0/src/allocate.o
enbid_ananke/Enbid-2.0/src/allvars.cpp
enbid_ananke/Enbid-2.0/src/allvars.h
enbid_ananke/Enbid-2.0/src/allvars.o
enbid_ananke/Enbid-2.0/src/begrun.cpp
enbid_ananke/Enbid-2.0/src/begrun.o
enbid_ananke/Enbid-2.0/src/density_nd.cpp
enbid_ananke/Enbid-2.0/src/density_nd.o
enbid_ananke/Enbid-2.0/src/functions.cpp
enbid_ananke/Enbid-2.0/src/functions.h
enbid_ananke/Enbid-2.0/src/functions.o
enbid_ananke/Enbid-2.0/src/init.cpp
enbid_ananke/Enbid-2.0/src/init.o
enbid_ananke/Enbid-2.0/src/io.cpp
enbid_ananke/Enbid-2.0/src/io.o
enbid_ananke/Enbid-2.0/src/main.cpp
enbid_ananke/Enbid-2.0/src/main.o
enbid_ananke/Enbid-2.0/src/ngb_search.cpp
enbid_ananke-0.3.1.dist-info/LICENSE
enbid_ananke-0.3.1.dist-info/METADATA
enbid_ananke-0.3.1.dist-info/WHEEL
enbid_ananke-0.3.1.dist-info/top_level.txt
enbid_ananke-0.3.1.dist-info/RECORD
