Metadata-Version: 2.1
Name: enbid_ananke
Version: 0.3.1
Summary: py-EnBiD-ananke: Python wrapper for EnBiD (Sharma & Steinmetz 2011 <http://ascl.net/1109.012>) for py-ananke <https://github.com/athob/py-ananke>.
Home-page: https://github.com/athob/py-EnBiD-ananke
Author: Adrien Thob
Author-email: athob@sas.upenn.edu
Maintainer: Adrien Thob
Maintainer-email: athob@sas.upenn.edu
License: GNU General Public License v2 or later (GPLv2+)
Classifier: Development Status :: 5 - Production/Stable
Classifier: Environment :: Console
Classifier: Intended Audience :: Science/Research
Classifier: License :: OSI Approved :: GNU General Public License v2 or later (GPLv2+)
Classifier: Natural Language :: English
Classifier: Operating System :: Unix
Classifier: Programming Language :: Python :: 3
Classifier: Topic :: Scientific/Engineering :: Astronomy
Requires-Python: >=3.8,<3.14
License-File: LICENSE
Requires-Dist: numpy <2,>=1.22
Requires-Dist: pandas <3,>=2
Requires-Dist: scikit-learn <2,>=1.1
